circlepathfinder-1.0.0.dist-info/licenses/LICENSE
pathfinder/__init__.py
pathfinder/pathfinder.py
circlepathfinder-1.0.0.dist-info/METADATA
circlepathfinder-1.0.0.dist-info/WHEEL
circlepathfinder-1.0.0.dist-info/top_level.txt
circlepathfinder-1.0.0.dist-info/RECORD
