Metadata-Version: 2.4
Name: CirclePathFinder
Version: 1.0.0
Summary: Pathfinding in constrained environments designed for navigating structured networks formed by intersecting circles.
Author-email: Michal Krupa <michalkrupa@gmail.com>
License-Expression: MIT
Project-URL: Homepage, https://github.com/michalkrupa/pathfinding/
Project-URL: Issues, https://github.com/michalkrupa/pathfinding/issues
Classifier: Programming Language :: Python :: 3
Classifier: Operating System :: OS Independent
Requires-Python: >=3.9
License-File: LICENSE
Requires-Dist: scipy<2.0,>=1.8
Dynamic: license-file
